{
 "ETag": "W/\"54edb47d93693c96fa75952bbefdb8c14244d51c4721c0063e9fd6482a3e319a\"",
 "Last-Modified": "Tue, 19 Jul 2022 03:50:13 GMT",
 "base": {
  "repo": {
   "name": "openfermion-feedstock"
  }
 },
 "closed_at": null,
 "created_at": "2022-07-19T03:50:09Z",
 "draft": false,
 "head": {
  "ref": "1.4.0_h631156"
 },
 "html_url": "https://github.com/conda-forge/openfermion-feedstock/pull/4",
 "id": 1000269352,
 "labels": [],
 "mergeable": true,
 "mergeable_state": "clean",
 "merged": false,
 "merged_at": null,
 "number": 4,
 "state": "open",
 "updated_at": "2022-07-19T03:50:13Z"
}