{
 "ETag": "W/\"5b4c1c278872b769ab5f665fdf9e59bf469a7d49d766dd48b5f0addaa4098076\"",
 "Last-Modified": "Fri, 06 Jan 2023 16:31:56 GMT",
 "base": {
  "repo": {
   "name": "fps-terminals-feedstock"
  }
 },
 "closed_at": null,
 "created_at": "2022-08-09T21:53:18Z",
 "draft": false,
 "head": {
  "ref": "rebuild-pypy38-0-1_h7e70e0"
 },
 "html_url": "https://github.com/conda-forge/fps-terminals-feedstock/pull/12",
 "id": 1022012444,
 "labels": [],
 "mergeable": true,
 "mergeable_state": "unstable",
 "merged": false,
 "merged_at": null,
 "number": 12,
 "state": "open",
 "updated_at": "2022-08-09T21:53:22Z"
}