{
 "ETag": "W/\"841e0fea83da3db8677c14709004d43bf9713f35c8bf8f1b27a8d4d717a2becc\"",
 "Last-Modified": "Mon, 15 Aug 2022 01:32:49 GMT",
 "base": {
  "repo": {
   "name": "conda-forge-pinning-feedstock"
  }
 },
 "closed_at": null,
 "created_at": "2022-08-10T03:24:38Z",
 "draft": false,
 "head": {
  "ref": "new_pin-libprotobuf-21.5-0-_h2dd464"
 },
 "html_url": "https://github.com/conda-forge/conda-forge-pinning-feedstock/pull/3223",
 "id": 1022173190,
 "labels": [],
 "mergeable": true,
 "mergeable_state": "clean",
 "merged": false,
 "merged_at": null,
 "number": 3223,
 "state": "open",
 "updated_at": "2022-08-15T01:32:49Z"
}