{
 "ETag": "W/\"b2f2528f1c4097e53668a55f8121b341b9f98ce74edf38c0e4a1ed44b40bdb3a\"",
 "Last-Modified": "Thu, 25 Aug 2022 03:40:33 GMT",
 "base": {
  "repo": {
   "name": "conda-standalone-feedstock"
  }
 },
 "closed_at": null,
 "created_at": "2022-08-25T03:40:29Z",
 "draft": false,
 "head": {
  "ref": "4.14.0_ha94fc1"
 },
 "html_url": "https://github.com/conda-forge/conda-standalone-feedstock/pull/43",
 "id": 1036208421,
 "labels": [],
 "mergeable": true,
 "mergeable_state": "unstable",
 "merged": false,
 "merged_at": null,
 "number": 43,
 "state": "open",
 "updated_at": "2022-08-25T03:40:33Z"
}