{
 "ETag": "W/\"43f781a4da278512bce3e3739f518805219869e361a95448b0c3824967dd4e08\"",
 "Last-Modified": "Wed, 14 Sep 2022 06:03:18 GMT",
 "base": {
  "repo": {
   "name": "geowombat-feedstock"
  }
 },
 "closed_at": null,
 "created_at": "2022-09-14T06:03:13Z",
 "draft": false,
 "head": {
  "ref": "2.0.2_h98bf7a"
 },
 "html_url": "https://github.com/conda-forge/geowombat-feedstock/pull/41",
 "id": 1055523543,
 "labels": [],
 "mergeable": true,
 "mergeable_state": "unstable",
 "merged": false,
 "merged_at": null,
 "number": 41,
 "state": "open",
 "updated_at": "2022-09-14T06:03:18Z"
}