{
 "ETag": "W/\"ae5923721be81ad31f1e6696a2b94e7c4aacfa1df97e517f1831646c5cabb99d\"",
 "Last-Modified": "Sun, 18 Sep 2022 10:56:34 GMT",
 "base": {
  "repo": {
   "name": "textdistance-feedstock"
  }
 },
 "closed_at": null,
 "created_at": "2022-09-18T10:56:30Z",
 "draft": false,
 "head": {
  "ref": "4.5.0_h00a331"
 },
 "html_url": "https://github.com/conda-forge/textdistance-feedstock/pull/16",
 "id": 1059512491,
 "labels": [],
 "mergeable": true,
 "mergeable_state": "clean",
 "merged": false,
 "merged_at": null,
 "number": 16,
 "state": "open",
 "updated_at": "2022-09-18T10:56:34Z"
}