{
 "ETag": "W/\"bde7e1d832ee0a332749d57970d6f1ba12ef1064244c0986a600de3b68b4b716\"",
 "Last-Modified": "Thu, 27 Oct 2022 04:33:56 GMT",
 "base": {
  "repo": {
   "name": "jasp-feedstock"
  }
 },
 "closed_at": null,
 "created_at": "2022-10-20T17:20:11Z",
 "draft": false,
 "head": {
  "ref": "rebuild-boost1780-0-3_hda6b09"
 },
 "html_url": "https://github.com/conda-forge/jasp-feedstock/pull/17",
 "id": 1094130018,
 "labels": [],
 "mergeable": null,
 "mergeable_state": "unknown",
 "merged": false,
 "merged_at": null,
 "number": 17,
 "state": "open",
 "updated_at": "2022-10-27T04:33:56Z"
}