{
 "ETag": "W/\"978ac0e047e5aa0f92b99bbbdd350d7295f4945d9e5bbf5b7e0d6e4ed95388da\"",
 "Last-Modified": "Mon, 31 Oct 2022 05:04:30 GMT",
 "base": {
  "repo": {
   "name": "pyxid-feedstock"
  }
 },
 "closed_at": null,
 "created_at": "2022-10-31T05:04:26Z",
 "draft": false,
 "head": {
  "ref": "rebuild-python311-0-1_haca737"
 },
 "html_url": "https://github.com/conda-forge/pyxid-feedstock/pull/8",
 "id": 1104837287,
 "labels": [],
 "mergeable": true,
 "mergeable_state": "unstable",
 "merged": false,
 "merged_at": null,
 "number": 8,
 "state": "open",
 "updated_at": "2022-10-31T05:04:30Z"
}