{
 "ETag": "W/\"7224113e695300dd9cba409739901d22a52cf831f1263ceffc75e0c18357f804\"",
 "Last-Modified": "Tue, 08 Nov 2022 19:22:40 GMT",
 "base": {
  "repo": {
   "name": "zc.buildout-feedstock"
  }
 },
 "closed_at": null,
 "created_at": "2022-11-08T18:45:33Z",
 "draft": false,
 "head": {
  "ref": "3.0.1_h4d219b"
 },
 "html_url": "https://github.com/conda-forge/zc.buildout-feedstock/pull/14",
 "id": 1114875142,
 "labels": [],
 "mergeable": true,
 "mergeable_state": "unstable",
 "merged": false,
 "merged_at": null,
 "number": 14,
 "state": "open",
 "updated_at": "2022-11-08T19:22:40Z"
}