{
 "ETag": "W/\"1d4397a1e494042d9736f40e5f4c70241be3623e7e05188dee7ad3b1c17e6aba\"",
 "Last-Modified": "Wed, 23 Nov 2022 00:48:12 GMT",
 "base": {
  "repo": {
   "name": "globus-sdk-feedstock"
  }
 },
 "closed_at": null,
 "created_at": "2022-11-23T00:48:07Z",
 "draft": false,
 "head": {
  "ref": "3.15.0_h91f5e2"
 },
 "html_url": "https://github.com/conda-forge/globus-sdk-feedstock/pull/37",
 "id": 1132602114,
 "labels": [],
 "mergeable": true,
 "mergeable_state": "clean",
 "merged": false,
 "merged_at": null,
 "number": 37,
 "state": "open",
 "updated_at": "2022-11-23T00:48:12Z"
}