{
 "ETag": "W/\"88b2b188000dbaa32443cf8f1b7c5f9a66355389ec2d3a769ce0df41206fbad9\"",
 "Last-Modified": "Fri, 16 Dec 2022 08:36:54 GMT",
 "base": {
  "repo": {
   "name": "mofchecker-feedstock"
  }
 },
 "closed_at": null,
 "created_at": "2022-12-15T23:02:51Z",
 "draft": false,
 "head": {
  "ref": "0.9.6_h0b5d5f"
 },
 "html_url": "https://github.com/conda-forge/mofchecker-feedstock/pull/7",
 "id": 1167503265,
 "labels": [],
 "mergeable": true,
 "mergeable_state": "unstable",
 "merged": false,
 "merged_at": null,
 "number": 7,
 "state": "open",
 "updated_at": "2022-12-16T08:36:54Z"
}