{
 "ETag": "W/\"6c73549f53762a46efd80ee8131ee3307331c87c291486833057161adea2f255\"",
 "Last-Modified": "Tue, 17 Jan 2023 11:35:21 GMT",
 "base": {
  "repo": {
   "name": "magic-feedstock"
  }
 },
 "closed_at": null,
 "created_at": "2023-01-17T11:34:01Z",
 "draft": false,
 "head": {
  "ref": "8.3.362_hcb0134"
 },
 "html_url": "https://github.com/conda-forge/magic-feedstock/pull/62",
 "id": 1200141889,
 "labels": [],
 "mergeable": true,
 "mergeable_state": "clean",
 "merged": false,
 "merged_at": null,
 "number": 62,
 "state": "open",
 "updated_at": "2023-01-17T11:35:21Z"
}