{
 "ETag": "W/\"649fc0a6af3aa2da281988ff02a28d79d6f6f26ad80c82802b1883f301d9789f\"",
 "Last-Modified": "Fri, 06 Nov 2020 22:48:06 GMT",
 "base": {
  "repo": {
   "name": "preact-feedstock"
  }
 },
 "closed_at": null,
 "created_at": "2020-08-04T20:02:54Z",
 "draft": false,
 "head": {
  "ref": "10.4.6_hfb5635"
 },
 "html_url": "https://github.com/conda-forge/preact-feedstock/pull/18",
 "id": 462979290,
 "labels": [],
 "mergeable": true,
 "mergeable_state": "unstable",
 "merged": false,
 "merged_at": null,
 "number": 18,
 "state": "open",
 "updated_at": "2020-08-04T20:02:58Z"
}