{
 "ETag": "W/\"9bbad83452b6e924fe718409a88195b2c79249b846047abe3b891a8ef6609c81\"",
 "Last-Modified": "Thu, 26 Nov 2020 15:39:35 GMT",
 "base": {
  "repo": {
   "name": "pyfakefs-feedstock"
  }
 },
 "closed_at": null,
 "created_at": "2020-11-26T15:39:30Z",
 "draft": false,
 "head": {
  "ref": "4.3.2_h5d129f"
 },
 "html_url": "https://github.com/conda-forge/pyfakefs-feedstock/pull/14",
 "id": 528152068,
 "labels": [],
 "mergeable": true,
 "mergeable_state": "clean",
 "merged": false,
 "merged_at": null,
 "number": 14,
 "state": "open",
 "updated_at": "2020-11-26T15:39:35Z"
}