{
 "ETag": "W/\"50b7df2e1d038126f6624856695222e043bd3477bef2f441168ef6f79b5fd06e\"",
 "Last-Modified": "Wed, 03 Feb 2021 00:32:59 GMT",
 "base": {
  "repo": {
   "name": "nionutils-feedstock"
  }
 },
 "closed_at": null,
 "created_at": "2021-02-03T00:32:55Z",
 "draft": false,
 "head": {
  "ref": "0.3.25_h088741"
 },
 "html_url": "https://github.com/conda-forge/nionutils-feedstock/pull/7",
 "id": 566428986,
 "labels": [],
 "mergeable": true,
 "mergeable_state": "clean",
 "merged": false,
 "merged_at": null,
 "number": 7,
 "state": "open",
 "updated_at": "2021-02-03T00:32:59Z"
}