{
 "ETag": "W/\"ed4ff258ac2ffbd0056a6526954be5c2dec5571b97573a7e878c1254acc155a1\"",
 "Last-Modified": "Mon, 14 Mar 2022 11:44:29 GMT",
 "base": {
  "repo": {
   "name": "shogun-feedstock"
  }
 },
 "closed_at": null,
 "created_at": "2021-02-10T15:06:38Z",
 "draft": false,
 "head": {
  "ref": "rebuild-pypy37-0-1_h768312"
 },
 "html_url": "https://github.com/conda-forge/shogun-feedstock/pull/33",
 "id": 571172329,
 "labels": [],
 "mergeable": true,
 "mergeable_state": "unstable",
 "merged": false,
 "merged_at": null,
 "number": 33,
 "state": "open",
 "updated_at": "2022-03-14T11:44:29Z"
}