{
 "ETag": "W/\"345db35f2440b3e31721cc8dee82e92e44891e9539c5ece9d2013d7e656cc00d\"",
 "Last-Modified": "Mon, 15 Feb 2021 11:42:30 GMT",
 "base": {
  "repo": {
   "name": "blocked-matrix-utils-feedstock"
  }
 },
 "closed_at": null,
 "created_at": "2021-02-15T11:35:22Z",
 "draft": false,
 "head": {
  "ref": "1.0.9_h629bb4"
 },
 "html_url": "https://github.com/conda-forge/blocked-matrix-utils-feedstock/pull/8",
 "id": 573497372,
 "labels": [],
 "mergeable": true,
 "mergeable_state": "clean",
 "merged": false,
 "merged_at": null,
 "number": 8,
 "state": "open",
 "updated_at": "2021-02-15T11:42:30Z"
}