{
 "ETag": "W/\"207fd73bda07a2406850fa5464e162e147862dd51bab575e65e215a2102b937b\"",
 "Last-Modified": "Thu, 18 Feb 2021 04:25:14 GMT",
 "base": {
  "repo": {
   "name": "nodejs-feedstock"
  }
 },
 "closed_at": null,
 "created_at": "2021-02-18T04:25:10Z",
 "draft": false,
 "head": {
  "ref": "15.9.0_hfef31b"
 },
 "html_url": "https://github.com/conda-forge/nodejs-feedstock/pull/177",
 "id": 575384056,
 "labels": [],
 "mergeable": true,
 "mergeable_state": "unstable",
 "merged": false,
 "merged_at": null,
 "number": 177,
 "state": "open",
 "updated_at": "2021-02-18T04:25:14Z"
}