{
 "ETag": "W/\"35f54122e359b616ea91e7950d93ed614d3298ed7a066a13f5504718f0518a4d\"",
 "Last-Modified": "Fri, 26 Mar 2021 17:44:37 GMT",
 "base": {
  "repo": {
   "name": "eo-learn-features-feedstock"
  }
 },
 "closed_at": null,
 "created_at": "2021-03-26T17:44:33Z",
 "draft": false,
 "head": {
  "ref": "0.9.0_h7c9a31"
 },
 "html_url": "https://github.com/conda-forge/eo-learn-features-feedstock/pull/8",
 "id": 601803511,
 "labels": [],
 "mergeable": true,
 "mergeable_state": "unstable",
 "merged": false,
 "merged_at": null,
 "number": 8,
 "state": "open",
 "updated_at": "2021-03-26T17:44:37Z"
}