{
 "ETag": "W/\"39f69a06fa797637e15afbd7e1f755b4453c2dc3174ae87c126ae4829ed31e7a\"",
 "Last-Modified": "Fri, 02 Apr 2021 17:05:00 GMT",
 "base": {
  "repo": {
   "name": "conda-forge-pinning-feedstock"
  }
 },
 "closed_at": null,
 "created_at": "2021-04-02T17:04:56Z",
 "draft": false,
 "head": {
  "ref": "new_pin-slepc-3.15-0-_he0ef8b"
 },
 "html_url": "https://github.com/conda-forge/conda-forge-pinning-feedstock/pull/1403",
 "id": 608132144,
 "labels": [],
 "mergeable": true,
 "mergeable_state": "clean",
 "merged": false,
 "merged_at": null,
 "number": 1403,
 "state": "open",
 "updated_at": "2021-04-02T17:05:00Z"
}