{
 "ETag": "W/\"78c64a2daa01bae70fea12e3d657fc26c6de0a520b01301a8c95a7e38855a2ab\"",
 "Last-Modified": "Wed, 26 May 2021 08:11:38 GMT",
 "base": {
  "repo": {
   "name": "clang-compiler-activation-feedstock"
  }
 },
 "closed_at": null,
 "created_at": "2021-05-14T05:38:07Z",
 "draft": false,
 "head": {
  "ref": "12.0.0_h874bd2"
 },
 "html_url": "https://github.com/conda-forge/clang-compiler-activation-feedstock/pull/62",
 "id": 644463802,
 "labels": [],
 "mergeable": true,
 "mergeable_state": "clean",
 "merged": false,
 "merged_at": null,
 "number": 62,
 "state": "open",
 "updated_at": "2021-05-26T08:11:38Z"
}