{
 "ETag": "W/\"7e00d43c7227bd1c92040757dde3081f3bc016090a2bafcc305deab4918b1df1\"",
 "Last-Modified": "Sat, 29 May 2021 20:18:54 GMT",
 "base": {
  "repo": {
   "name": "r-arrow-feedstock"
  }
 },
 "closed_at": null,
 "created_at": "2021-05-29T19:35:48Z",
 "draft": false,
 "head": {
  "ref": "4.0.1_hdfd88d"
 },
 "html_url": "https://github.com/conda-forge/r-arrow-feedstock/pull/36",
 "id": 657524276,
 "labels": [
  {
   "color": "0e8a16",
   "default": false,
   "description": "Merge the PR when CI passes",
   "id": 1891179657,
   "name": "automerge",
   "node_id": "MDU6TGFiZWwxODkxMTc5NjU3",
   "url": "https://api.github.com/repos/conda-forge/r-arrow-feedstock/labels/automerge"
  }
 ],
 "mergeable": true,
 "mergeable_state": "unstable",
 "merged": false,
 "merged_at": null,
 "number": 36,
 "state": "open",
 "updated_at": "2021-05-29T20:18:54Z"
}