{
 "ETag": "W/\"c8546214d2816221f9f712d9fad7180309193d16a62ee7f4e4ca56c63ac05734\"",
 "Last-Modified": "Thu, 17 Jun 2021 10:49:58 GMT",
 "base": {
  "repo": {
   "name": "pytorch_geometric-feedstock"
  }
 },
 "closed_at": null,
 "created_at": "2021-06-17T10:49:54Z",
 "draft": false,
 "head": {
  "ref": "1.7.1_hfc5188"
 },
 "html_url": "https://github.com/conda-forge/pytorch_geometric-feedstock/pull/9",
 "id": 672505425,
 "labels": [],
 "mergeable": true,
 "mergeable_state": "unstable",
 "merged": false,
 "merged_at": null,
 "number": 9,
 "state": "open",
 "updated_at": "2021-06-17T10:49:58Z"
}