{
 "ETag": "W/\"2d0a875dd91038df0b4560471e3276556675ec601f9b69cbe8f29bae56ea0437\"",
 "Last-Modified": "Fri, 02 Jul 2021 01:58:58 GMT",
 "base": {
  "repo": {
   "name": "pyuvdata-feedstock"
  }
 },
 "closed_at": null,
 "created_at": "2021-07-02T00:48:13Z",
 "draft": false,
 "head": {
  "ref": "2.2.0_h6f69e6"
 },
 "html_url": "https://github.com/conda-forge/pyuvdata-feedstock/pull/31",
 "id": 682256420,
 "labels": [],
 "mergeable": true,
 "mergeable_state": "unstable",
 "merged": false,
 "merged_at": null,
 "number": 31,
 "state": "open",
 "updated_at": "2021-07-02T01:58:58Z"
}