{
 "ETag": "W/\"8d523663a62c39ab7930c13f7f8a699b61fff42eb91803007c8ce09979c3dbd8\"",
 "Last-Modified": "Wed, 15 Sep 2021 16:01:31 GMT",
 "base": {
  "repo": {
   "name": "psy-simple-feedstock"
  }
 },
 "closed_at": null,
 "created_at": "2021-08-31T06:56:44Z",
 "draft": false,
 "head": {
  "ref": "rebuild-pypy37-windows-0-1_h05fc59"
 },
 "html_url": "https://github.com/conda-forge/psy-simple-feedstock/pull/13",
 "id": 723076532,
 "labels": [],
 "mergeable": true,
 "mergeable_state": "clean",
 "merged": false,
 "merged_at": null,
 "number": 13,
 "state": "open",
 "updated_at": "2021-09-15T16:01:31Z"
}