{
 "ETag": "W/\"861527876602d6ac094e90f5b08d82318faf1365ce724d8794a43d2351fcd665\"",
 "Last-Modified": "Tue, 21 Sep 2021 07:27:11 GMT",
 "base": {
  "repo": {
   "name": "websockets-feedstock"
  }
 },
 "closed_at": null,
 "created_at": "2021-09-21T07:27:07Z",
 "draft": false,
 "head": {
  "ref": "rebuild-broken-migration-2_h6da21b"
 },
 "html_url": "https://github.com/conda-forge/websockets-feedstock/pull/24",
 "id": 738438898,
 "labels": [],
 "mergeable": true,
 "mergeable_state": "unstable",
 "merged": false,
 "merged_at": null,
 "number": 24,
 "state": "open",
 "updated_at": "2021-09-21T07:27:11Z"
}