{
 "ETag": "W/\"5b0766cd7c043b1bb6432bf048d8b2e6aea5299b34da2e4adfdedb56ee5ec522\"",
 "Last-Modified": "Sat, 30 Oct 2021 19:37:24 GMT",
 "base": {
  "repo": {
   "name": "gdal-feedstock"
  }
 },
 "closed_at": null,
 "created_at": "2021-10-05T07:32:05Z",
 "draft": false,
 "head": {
  "ref": "rebuild-poppler2110-0-1_h2b92db"
 },
 "html_url": "https://github.com/conda-forge/gdal-feedstock/pull/540",
 "id": 749589423,
 "labels": [],
 "mergeable": true,
 "mergeable_state": "unstable",
 "merged": false,
 "merged_at": null,
 "number": 540,
 "state": "open",
 "updated_at": "2021-10-30T19:37:24Z"
}