{
 "ETag": "W/\"de95b9ba7589879ac9c3f86781d8a7e41c894fac5d13ad01ec30401a1c86b48b\"",
 "Last-Modified": "Wed, 08 Dec 2021 09:19:59 GMT",
 "base": {
  "repo": {
   "name": "mysql-connector-odbc-feedstock"
  }
 },
 "closed_at": null,
 "created_at": "2021-10-19T12:03:37Z",
 "draft": false,
 "head": {
  "ref": "8.0.27_he37f72"
 },
 "html_url": "https://github.com/conda-forge/mysql-connector-odbc-feedstock/pull/7",
 "id": 761360968,
 "labels": [
  {
   "color": "191970",
   "default": false,
   "description": "Instruct the bot to retry the PR",
   "id": 2728004831,
   "name": "bot-rerun",
   "node_id": "MDU6TGFiZWwyNzI4MDA0ODMx",
   "url": "https://api.github.com/repos/conda-forge/mysql-connector-odbc-feedstock/labels/bot-rerun"
  }
 ],
 "mergeable": true,
 "mergeable_state": "unstable",
 "merged": false,
 "merged_at": null,
 "number": 7,
 "state": "open",
 "updated_at": "2021-12-08T09:19:59Z"
}