{
 "ETag": "W/\"250298851bd8cd018d03105022231dc1c74db53cf4ed5f688ab1a625755f48c0\"",
 "Last-Modified": "Fri, 29 Oct 2021 01:33:42 GMT",
 "base": {
  "repo": {
   "name": "xerces-c-feedstock"
  }
 },
 "closed_at": null,
 "created_at": "2021-10-28T17:09:06Z",
 "draft": false,
 "head": {
  "ref": "rebuild-icu69-0-1_h1240de"
 },
 "html_url": "https://github.com/conda-forge/xerces-c-feedstock/pull/31",
 "id": 768542868,
 "labels": [],
 "mergeable": true,
 "mergeable_state": "clean",
 "merged": false,
 "merged_at": null,
 "number": 31,
 "state": "open",
 "updated_at": "2021-10-29T01:33:42Z"
}