{
 "ETag": "W/\"9d2c9b9ac16da9a8fa1b41d060b1d699e09e044243b476ef7e6387ec3c9996ff\"",
 "Last-Modified": "Fri, 05 Nov 2021 09:33:36 GMT",
 "base": {
  "repo": {
   "name": "boost-histogram-feedstock"
  }
 },
 "closed_at": null,
 "created_at": "2021-11-05T03:33:15Z",
 "draft": false,
 "head": {
  "ref": "rebuild-python310-0-1_hf0ea9d"
 },
 "html_url": "https://github.com/conda-forge/boost-histogram-feedstock/pull/40",
 "id": 773881807,
 "labels": [],
 "mergeable": true,
 "mergeable_state": "unstable",
 "merged": false,
 "merged_at": null,
 "number": 40,
 "state": "open",
 "updated_at": "2021-11-05T09:33:36Z"
}