{
 "ETag": "W/\"1ed4e38f7356bb9e8cfa5749d4966b6bb7260abb3a33f33a9301b4b2e18e4b8a\"",
 "Last-Modified": "Sat, 20 Nov 2021 11:40:41 GMT",
 "base": {
  "repo": {
   "name": "jaxlib-feedstock"
  }
 },
 "closed_at": null,
 "created_at": "2021-11-20T07:00:54Z",
 "draft": false,
 "head": {
  "ref": "0.1.74_h58c12e"
 },
 "html_url": "https://github.com/conda-forge/jaxlib-feedstock/pull/75",
 "id": 785163198,
 "labels": [],
 "mergeable": true,
 "mergeable_state": "unstable",
 "merged": false,
 "merged_at": null,
 "number": 75,
 "state": "open",
 "updated_at": "2021-11-20T11:40:41Z"
}