{
 "ETag": "W/\"5addc97f1621513b4a0749e08e33514a4f3810b57e912727c1a82e200df9b4de\"",
 "Last-Modified": "Sun, 05 Dec 2021 14:40:48 GMT",
 "base": {
  "repo": {
   "name": "django-cors-headers-feedstock"
  }
 },
 "closed_at": null,
 "created_at": "2021-12-05T14:40:44Z",
 "draft": false,
 "head": {
  "ref": "3.10.1_h225d2c"
 },
 "html_url": "https://github.com/conda-forge/django-cors-headers-feedstock/pull/25",
 "id": 795308500,
 "labels": [],
 "mergeable": true,
 "mergeable_state": "clean",
 "merged": false,
 "merged_at": null,
 "number": 25,
 "state": "open",
 "updated_at": "2021-12-05T14:40:48Z"
}