{
 "ETag": "W/\"0a4e974cc8e62f367c92f5df3cc8b62de2bf9485bcbd85c58eb7e847ec2e644a\"",
 "Last-Modified": "Wed, 12 Jan 2022 06:39:54 GMT",
 "base": {
  "repo": {
   "name": "coin-or-clp-feedstock"
  }
 },
 "closed_at": null,
 "created_at": "2022-01-12T06:39:51Z",
 "draft": false,
 "head": {
  "ref": "1.17.7_h28870c"
 },
 "html_url": "https://github.com/conda-forge/coin-or-clp-feedstock/pull/12",
 "id": 819357268,
 "labels": [],
 "mergeable": true,
 "mergeable_state": "clean",
 "merged": false,
 "merged_at": null,
 "number": 12,
 "state": "open",
 "updated_at": "2022-01-12T06:39:54Z"
}