{
 "ETag": "W/\"cd881d2c8d33e3b50099c4d1b213467d7015b10848cf4d321886c9b327fb5841\"",
 "Last-Modified": "Sat, 12 Mar 2022 21:33:48 GMT",
 "base": {
  "repo": {
   "name": "codechecker-feedstock"
  }
 },
 "closed_at": null,
 "created_at": "2022-01-14T14:13:51Z",
 "draft": false,
 "head": {
  "ref": "6.18.2_h744ad4"
 },
 "html_url": "https://github.com/conda-forge/codechecker-feedstock/pull/3",
 "id": 822722155,
 "labels": [],
 "mergeable": true,
 "mergeable_state": "clean",
 "merged": false,
 "merged_at": null,
 "number": 3,
 "state": "open",
 "updated_at": "2022-03-12T21:33:48Z"
}