{
 "ETag": "W/\"f0fd0ea201b9eeb1a6ed6e2ac670ffc1a529569c95e93f01e77d12b2e9b9c3e0\"",
 "Last-Modified": "Sun, 23 Jan 2022 14:12:15 GMT",
 "base": {
  "repo": {
   "name": "pdpipe-feedstock"
  }
 },
 "closed_at": null,
 "created_at": "2022-01-23T14:12:11Z",
 "draft": false,
 "head": {
  "ref": "0.1.0_hdcb8fe"
 },
 "html_url": "https://github.com/conda-forge/pdpipe-feedstock/pull/24",
 "id": 829757456,
 "labels": [],
 "mergeable": true,
 "mergeable_state": "unstable",
 "merged": false,
 "merged_at": null,
 "number": 24,
 "state": "open",
 "updated_at": "2022-01-23T14:12:15Z"
}