{
 "ETag": "W/\"3610783a8bc638ca37a750a12b632a67d0b3128826e83dc5e7d0c0aee161dccf\"",
 "Last-Modified": "Sat, 12 Mar 2022 16:25:28 GMT",
 "base": {
  "repo": {
   "name": "diceware-feedstock"
  }
 },
 "closed_at": null,
 "created_at": "2022-02-15T07:33:27Z",
 "draft": false,
 "head": {
  "ref": "0.10_hb38812"
 },
 "html_url": "https://github.com/conda-forge/diceware-feedstock/pull/2",
 "id": 852920173,
 "labels": [],
 "mergeable": null,
 "mergeable_state": "unknown",
 "merged": false,
 "merged_at": null,
 "number": 2,
 "state": "open",
 "updated_at": "2022-03-12T16:25:28Z"
}