{
 "ETag": "W/\"797003d7ba933727fc94cc54b406fb44bcfd89033da1fefce48584599101a84c\"",
 "Last-Modified": "Fri, 25 Feb 2022 12:46:59 GMT",
 "base": {
  "repo": {
   "name": "eigenpy-feedstock"
  }
 },
 "closed_at": null,
 "created_at": "2022-02-25T12:46:54Z",
 "draft": false,
 "head": {
  "ref": "2.6.11_h80fa04"
 },
 "html_url": "https://github.com/conda-forge/eigenpy-feedstock/pull/77",
 "id": 863408263,
 "labels": [],
 "mergeable": true,
 "mergeable_state": "unstable",
 "merged": false,
 "merged_at": null,
 "number": 77,
 "state": "open",
 "updated_at": "2022-02-25T12:46:59Z"
}