{
 "ETag": "W/\"ddb00aa3fb4b7f99f9271624a76c96e1c8fcdb79645920c50053b43d9aa088f0\"",
 "Last-Modified": "Tue, 01 Mar 2022 23:12:17 GMT",
 "base": {
  "repo": {
   "name": "tiledb-feedstock"
  }
 },
 "closed_at": null,
 "created_at": "2022-03-01T23:12:13Z",
 "draft": false,
 "head": {
  "ref": "2.7.0_ha02262"
 },
 "html_url": "https://github.com/conda-forge/tiledb-feedstock/pull/140",
 "id": 868372591,
 "labels": [],
 "mergeable": true,
 "mergeable_state": "unstable",
 "merged": false,
 "merged_at": null,
 "number": 140,
 "state": "open",
 "updated_at": "2022-03-01T23:12:17Z"
}