{
 "ETag": "W/\"b93758b1f29c6d086cf82674dd9424be7adb5f41c902c9ed31c433713c38ce0f\"",
 "Last-Modified": "Mon, 14 Mar 2022 23:01:05 GMT",
 "base": {
  "repo": {
   "name": "alembic-feedstock"
  }
 },
 "closed_at": null,
 "created_at": "2022-03-14T23:00:59Z",
 "draft": false,
 "head": {
  "ref": "1.7.7_he2faa2"
 },
 "html_url": "https://github.com/conda-forge/alembic-feedstock/pull/62",
 "id": 879601641,
 "labels": [],
 "mergeable": true,
 "mergeable_state": "clean",
 "merged": false,
 "merged_at": null,
 "number": 62,
 "state": "open",
 "updated_at": "2022-03-14T23:01:05Z"
}