{
 "ETag": "W/\"2c3030777237c26e0aa98ea7abfc3bfb8824ef1562528ae3b5a4710d359c8a56\"",
 "Last-Modified": "Thu, 17 Mar 2022 22:29:08 GMT",
 "base": {
  "repo": {
   "name": "pyfakefs-feedstock"
  }
 },
 "closed_at": null,
 "created_at": "2022-03-17T22:29:04Z",
 "draft": false,
 "head": {
  "ref": "4.5.6_ha9063a"
 },
 "html_url": "https://github.com/conda-forge/pyfakefs-feedstock/pull/23",
 "id": 882947126,
 "labels": [],
 "mergeable": true,
 "mergeable_state": "clean",
 "merged": false,
 "merged_at": null,
 "number": 23,
 "state": "open",
 "updated_at": "2022-03-17T22:29:08Z"
}