{
 "ETag": "W/\"569679afb9b94d36586b9d1ba01ac4c209d17248ca3df8b9ed06f039c2734f51\"",
 "Last-Modified": "Sat, 26 Mar 2022 21:46:11 GMT",
 "base": {
  "repo": {
   "name": "restic-feedstock"
  }
 },
 "closed_at": null,
 "created_at": "2022-03-26T21:46:07Z",
 "draft": false,
 "head": {
  "ref": "0.13.0_hc55c5c"
 },
 "html_url": "https://github.com/conda-forge/restic-feedstock/pull/9",
 "id": 890657177,
 "labels": [],
 "mergeable": true,
 "mergeable_state": "unstable",
 "merged": false,
 "merged_at": null,
 "number": 9,
 "state": "open",
 "updated_at": "2022-03-26T21:46:11Z"
}