{
 "ETag": "W/\"61872249021d4b435735ba5b70f08d367202c2ad8228173f81403244175cd880\"",
 "Last-Modified": "Thu, 14 Apr 2022 11:52:00 GMT",
 "base": {
  "repo": {
   "name": "goodvibes-feedstock"
  }
 },
 "closed_at": null,
 "created_at": "2022-04-11T14:02:47Z",
 "draft": false,
 "head": {
  "ref": "rebuild-python310-0-1_he9723c"
 },
 "html_url": "https://github.com/conda-forge/goodvibes-feedstock/pull/1",
 "id": 906047915,
 "labels": [],
 "mergeable": true,
 "mergeable_state": "clean",
 "merged": false,
 "merged_at": null,
 "number": 1,
 "state": "open",
 "updated_at": "2022-04-14T11:52:00Z"
}