{
 "ETag": "W/\"d66059c95690b1d337ae81e6bea999e08e568509a8fdc365b53cce9d0ae3400d\"",
 "Last-Modified": "Fri, 27 May 2022 04:14:24 GMT",
 "base": {
  "repo": {
   "name": "fermipy-feedstock"
  }
 },
 "closed_at": null,
 "created_at": "2022-05-27T04:14:20Z",
 "draft": false,
 "head": {
  "ref": "1.1.2_h390b94"
 },
 "html_url": "https://github.com/conda-forge/fermipy-feedstock/pull/53",
 "id": 948916398,
 "labels": [],
 "mergeable": null,
 "mergeable_state": "unknown",
 "merged": false,
 "merged_at": null,
 "number": 53,
 "state": "open",
 "updated_at": "2022-05-27T04:14:24Z"
}