{
 "ETag": "W/\"8b212982d0db4b2f86e7039884a041d47c9965ec91ee7f28f7947d1f72edb470\"",
 "Last-Modified": "Sun, 12 Jun 2022 16:53:47 GMT",
 "base": {
  "repo": {
   "name": "conda-forge-pinning-feedstock"
  }
 },
 "closed_at": null,
 "created_at": "2022-06-12T16:53:42Z",
 "draft": false,
 "head": {
  "ref": "new_pin-poco-1.11.3-0-_h1decd7"
 },
 "html_url": "https://github.com/conda-forge/conda-forge-pinning-feedstock/pull/2988",
 "id": 965045283,
 "labels": [],
 "mergeable": true,
 "mergeable_state": "clean",
 "merged": false,
 "merged_at": null,
 "number": 2988,
 "state": "open",
 "updated_at": "2022-06-12T16:53:47Z"
}