{
 "ETag": "W/\"c74ec57e59c1c77bf1315394a08cbceb877685d819a041d44bf0c4f47d075ef7\"",
 "Last-Modified": "Tue, 05 Jul 2022 22:10:55 GMT",
 "base": {
  "repo": {
   "name": "conda-forge-pinning-feedstock"
  }
 },
 "closed_at": null,
 "created_at": "2022-07-05T22:10:51Z",
 "draft": false,
 "head": {
  "ref": "rebuild-aws_c_event_stream028-0-1_hd91fd5"
 },
 "html_url": "https://github.com/conda-forge/conda-forge-pinning-feedstock/pull/3077",
 "id": 987900544,
 "labels": [],
 "mergeable": true,
 "mergeable_state": "clean",
 "merged": false,
 "merged_at": null,
 "number": 3077,
 "state": "open",
 "updated_at": "2022-07-05T22:10:55Z"
}