{
 "ETag": "W/\"63ba181da5850619b5b91d7afff32fe1fa862f610f4518c24a1561df2881c0ca\"",
 "Last-Modified": "Wed, 06 Jul 2022 04:20:54 GMT",
 "base": {
  "repo": {
   "name": "conda-forge-pinning-feedstock"
  }
 },
 "closed_at": null,
 "created_at": "2022-07-06T04:20:50Z",
 "draft": false,
 "head": {
  "ref": "new_pin-aws_sdk_cpp-1.9.292-0-_h4ec7d6"
 },
 "html_url": "https://github.com/conda-forge/conda-forge-pinning-feedstock/pull/3083",
 "id": 988138846,
 "labels": [],
 "mergeable": true,
 "mergeable_state": "clean",
 "merged": false,
 "merged_at": null,
 "number": 3083,
 "state": "open",
 "updated_at": "2022-07-06T04:20:54Z"
}