{
 "ETag": "W/\"8d1f1ff3529196b92729faf2f54f403efa8c5cdee61e95a042feddef3a3167cb\"",
 "Last-Modified": "Mon, 18 Jul 2022 16:25:43 GMT",
 "base": {
  "repo": {
   "name": "pandas-stubs-feedstock"
  }
 },
 "closed_at": null,
 "created_at": "2022-07-18T16:16:52Z",
 "draft": false,
 "head": {
  "ref": "1.4.3.220718_hac142c"
 },
 "html_url": "https://github.com/conda-forge/pandas-stubs-feedstock/pull/106",
 "id": 999600407,
 "labels": [],
 "mergeable": true,
 "mergeable_state": "unstable",
 "merged": false,
 "merged_at": null,
 "number": 106,
 "state": "open",
 "updated_at": "2022-07-18T16:25:43Z"
}