{
 "builtin": {
  "__set__": true,
  "elements": [
   "Queue",
   "StringIO",
   "__future__",
   "__main__",
   "_ctypes",
   "_thread",
   "array",
   "base64",
   "cPickle",
   "cStringIO",
   "codecs",
   "collections",
   "copy",
   "csv",
   "ctypes",
   "distutils.command",
   "distutils.core",
   "fcntl",
   "gc",
   "getpass",
   "glob",
   "hashlib",
   "imp",
   "importlib",
   "io",
   "json",
   "math",
   "md5",
   "mmap",
   "multiprocessing",
   "optparse",
   "os",
   "pdb",
   "pickle",
   "platform",
   "queue",
   "random",
   "re",
   "readline",
   "resource",
   "sha",
   "shlex",
   "shutil",
   "socket",
   "sqlite3",
   "string",
   "struct",
   "sys",
   "tarfile",
   "tempfile",
   "termios",
   "textwrap",
   "thread",
   "threading",
   "time",
   "trace",
   "traceback",
   "unittest",
   "urllib.request",
   "urllib2",
   "warnings",
   "weakref",
   "zipfile",
   "zlib"
  ]
 },
 "questionable": {
  "__set__": true,
  "elements": [
   "apsw",
   "colorama",
   "coverage",
   "pygments",
   "setuptools",
   "simplejson"
  ]
 },
 "questionable no match": {
  "__set__": true,
  "elements": [
   "pysqlite2"
  ]
 },
 "required": {
  "__set__": true,
  "elements": [
   "apsw"
  ]
 },
 "required no match": {
  "__set__": true,
  "elements": [
   "speedtest"
  ]
 }
}