{
 "builtin": {
  "__set__": true,
  "elements": [
   "__future__",
   "enum",
   "functools",
   "io",
   "os",
   "pkgutil",
   "sys",
   "traceback",
   "warnings"
  ]
 },
 "questionable": {
  "__set__": true,
  "elements": [
   "google-api-core",
   "google-cloud-error-reporting",
   "setuptools"
  ]
 },
 "required": {
  "__set__": true,
  "elements": [
   "google-api-core",
   "google-cloud-core",
   "google-cloud-error-reporting",
   "google-cloud-logging",
   "grpcio",
   "protobuf",
   "setuptools",
   "six"
  ]
 }
}