{
 "builtin": {
  "__set__": true,
  "elements": [
   "__future__",
   "argparse",
   "bz2",
   "cPickle",
   "datetime",
   "email.mime.image",
   "email.mime.multipart",
   "email.mime.text",
   "functools",
   "importlib",
   "inspect",
   "io",
   "logging",
   "multiprocessing",
   "os",
   "pickle",
   "random",
   "re",
   "smtplib",
   "socket",
   "sys",
   "time",
   "traceback"
  ]
 },
 "questionable": {
  "__set__": true,
  "elements": [
   "drmaa",
   "matplotlib"
  ]
 },
 "questionable no match": {
  "__set__": true,
  "elements": []
 },
 "required": {
  "__set__": true,
  "elements": [
   "cherrypy",
   "cloudpickle",
   "gridmap",
   "psutil",
   "pyzmq",
   "setuptools"
  ]
 },
 "required no match": {
  "__set__": true,
  "elements": []
 }
}