{
 "builtin": {
  "__set__": true,
  "elements": [
   "contextlib",
   "copy",
   "datetime",
   "os",
   "shutil",
   "subprocess",
   "tempfile",
   "warnings"
  ]
 },
 "questionable": {
  "__set__": true,
  "elements": [
   "pandas"
  ]
 },
 "questionable no match": {
  "__set__": true,
  "elements": []
 },
 "required": {
  "__set__": true,
  "elements": [
   "mbuild",
   "mosdef_cassandra",
   "numpy",
   "parmed",
   "setuptools",
   "unyt"
  ]
 },
 "required no match": {
  "__set__": true,
  "elements": []
 }
}