{
 "builtin":{
  "__set__":true,
  "elements":[
   "codecs",
   "collections",
   "colorsys",
   "copy",
   "ctypes",
   "difflib",
   "distutils",
   "fcntl",
   "fnmatch",
   "functools",
   "gc",
   "imp",
   "inspect",
   "io",
   "itertools",
   "json",
   "logging",
   "math",
   "multiprocessing",
   "numbers",
   "operator",
   "optparse",
   "pickle",
   "platform",
   "random",
   "re",
   "shlex",
   "shutil",
   "signal",
   "site",
   "string",
   "struct",
   "subprocess",
   "sys",
   "tarfile",
   "tempfile",
   "textwrap",
   "threading",
   "time",
   "tkinter",
   "traceback",
   "types",
   "urllib",
   "warnings",
   "webbrowser",
   "whitebox"
  ]
 },
 "questionable":{
  "__set__":true,
  "elements":[
   "PyQt5",
   "Quest",
   "Tkinter",
   "android",
   "billiard",
   "certifi",
   "datamatrix",
   "fileinspector",
   "json_tricks",
   "libopensesame",
   "libqtopensesame",
   "markdown",
   "numpy",
   "openexp",
   "parallel",
   "pillow",
   "plugin_manager_widget",
   "psychopy",
   "pygame",
   "pygments",
   "pyqode.qt",
   "pyqode_extras",
   "pyqode_preferences",
   "pyyaml",
   "qdatamatrix",
   "qtpy",
   "scipy",
   "shapely",
   "sip",
   "stdeb3",
   "urllib2",
   "yamldoc"
  ]
 },
 "required":{
  "__set__":true,
  "elements":[
   "PyQt4",
   "PyQt5",
   "billiard",
   "cv",
   "datamatrix",
   "expyriment",
   "libopensesame",
   "libqtopensesame",
   "libsrbox",
   "numpy",
   "openexp",
   "oscoroutines",
   "pillow",
   "plugin_manager_widget",
   "pseudorandom",
   "psychopy",
   "pygame",
   "pyglet",
   "pygments",
   "pyqode.qt",
   "pyqode_extras",
   "pyserial",
   "pysoundfile",
   "pyyaml",
   "qdatamatrix",
   "qnotifications",
   "qtpy",
   "setup_shared",
   "setuptools",
   "sip",
   "tab_to_dockwidget_docktab",
   "undo_stack",
   "urllib2",
   "variable_inspector_cell",
   "variable_inspector_dockwidget",
   "variable_inspector_widget",
   "webcolors"
  ]
 }
}