{
 "builtin":{
  "__set__":true,
  "elements":[
   "__future__",
   "collections",
   "configparser",
   "datetime",
   "decimal",
   "distutils",
   "enum34",
   "errno",
   "hashlib",
   "ipaddress",
   "itertools",
   "json",
   "re",
   "socket",
   "ssl",
   "struct",
   "subprocess",
   "sys",
   "time",
   "uuid",
   "warnings",
   "whitebox"
  ]
 },
 "questionable":{
  "__set__":true,
  "elements":[
   "ConfigParser",
   "cx_freeze",
   "setuptools"
  ]
 },
 "relative":{
  "__set__":true,
  "elements":[
   "_version"
  ]
 },
 "required":{
  "__set__":true,
  "elements":[
   "pg8000",
   "scramp",
   "setuptools",
   "versioneer"
  ]
 }
}