{
 "builtin": {
  "__set__": true,
  "elements": [
   "StringIO",
   "__future__",
   "_thread",
   "_warnings",
   "base64",
   "binascii",
   "cProfile",
   "cgi",
   "collections",
   "contextlib",
   "copy",
   "csv",
   "datetime",
   "decimal",
   "distutils",
   "email",
   "email.encoders",
   "email.message",
   "email.mime.application",
   "email.mime.multipart",
   "email.mime.text",
   "email.utils",
   "errno",
   "fcntl",
   "fnmatch",
   "functools",
   "gc",
   "getpass",
   "glob",
   "gzip",
   "hashlib",
   "inspect",
   "io",
   "itertools",
   "json",
   "logging",
   "math",
   "mmap",
   "multiprocessing",
   "multiprocessing.pool",
   "operator",
   "optparse",
   "os",
   "os.path",
   "platform",
   "pprint",
   "re",
   "shutil",
   "site",
   "smtplib",
   "socket",
   "struct",
   "subprocess",
   "sys",
   "tarfile",
   "tempfile",
   "thread",
   "threading",
   "time",
   "traceback",
   "types",
   "urllib",
   "urllib.error",
   "urllib.parse",
   "urllib.request",
   "urllib2",
   "uuid",
   "warnings",
   "weakref"
  ]
 },
 "questionable": {
  "__set__": true,
  "elements": [
   "colorama",
   "coverage",
   "django",
   "lxml",
   "msgpack-python",
   "psycopg2",
   "pytest",
   "pytz",
   "pyyaml",
   "setuptools",
   "simplejson",
   "spyne",
   "sqlalchemy",
   "tox",
   "twisted",
   "werkzeug"
  ]
 },
 "questionable no match": {
  "__set__": true,
  "elements": [
   "_preamble",
   "_systemrestart"
  ]
 },
 "required": {
  "__set__": true,
  "elements": [
   "cherrypy",
   "django",
   "lxml",
   "msgpack-python",
   "pyparsing",
   "pyramid",
   "pytz",
   "pyyaml",
   "pyzmq",
   "setuptools",
   "spyne",
   "sqlalchemy",
   "twisted",
   "zope.interface"
  ]
 },
 "required no match": {
  "__set__": true,
  "elements": []
 }
}